loghero/__init__.py
loghero/admin.py
loghero/apps.py
loghero/manager.py
loghero/models.py
loghero/tests.py
loghero/migrations/0001_initial.py
loghero/migrations/0002_alter_log_extra_data.py
loghero/migrations/0003_alter_log_status.py
loghero/migrations/0004_log_actor_label.py
loghero/migrations/__init__.py
loghero-1.2.2.dist-info/METADATA
loghero-1.2.2.dist-info/WHEEL
loghero-1.2.2.dist-info/licenses/LICENSE
loghero-1.2.2.dist-info/RECORD
