Metadata-Version: 2.4
Name: loghero
Version: 1.2.2
Summary: Simple app for log some generic infos on db in a structured way
Project-URL: Homepage, https://github.com/rh363/log-hero
Project-URL: Issues, https://github.com/rh363/log-hero/issues
License: This is free and unencumbered software released into the public domain.
License-File: LICENSE
Classifier: Environment :: Web Environment
Classifier: Intended Audience :: Developers
Classifier: License :: OSI Approved :: The Unlicense (Unlicense)
Classifier: Operating System :: OS Independent
Classifier: Programming Language :: Python :: 3 :: Only
Classifier: Programming Language :: Python :: 3.8
Classifier: Programming Language :: Python :: 3.9
Classifier: Programming Language :: Python :: 3.10
Classifier: Programming Language :: Python :: 3.11
Classifier: Programming Language :: Python :: 3.12
Classifier: Topic :: Software Development :: Libraries :: Application Frameworks
Classifier: Topic :: Software Development :: Libraries :: Python Modules
Requires-Python: >=3.0
Requires-Dist: asgiref>=3.8.1
Requires-Dist: certifi>=2024.8.30
Requires-Dist: charset-normalizer>=3.4.0
Requires-Dist: django>=4.2
Requires-Dist: hostip-client>=1.0.4
Requires-Dist: idna>=3.10
Requires-Dist: requests>=2.32.3
Requires-Dist: sqlparse>=0.5.2
Requires-Dist: urllib3>=2.2.3
